lazytool/Download.py
lazytool/__init__.py
lazytool/common.py
lazytool-114514.114514.1919810.1.dist-info/LICENSE
lazytool-114514.114514.1919810.1.dist-info/METADATA
lazytool-114514.114514.1919810.1.dist-info/WHEEL
lazytool-114514.114514.1919810.1.dist-info/top_level.txt
lazytool-114514.114514.1919810.1.dist-info/RECORD
