Metadata-Version: 2.1
Name: lazytool
Version: 114514.114514.1919810.1
Summary: lazytool
Home-page: http://test.com
Author: PhiTea
Author-email: hellogwkki@outlook.com
License: MIT License
Keywords: lazy,tools
Platform: any
